Metadata-Version: 1.0
Name: packagepg
Version: 1.0
Summary: len of random name
Home-page: UNKNOWN
Author: pg
Author-email: UNKNOWN
License: UNKNOWN
Platform: UNKNOWN
